ctg_mcp_server/__init__.py
ctg_mcp_server-0.1.0.dist-info/METADATA
ctg_mcp_server-0.1.0.dist-info/WHEEL
ctg_mcp_server-0.1.0.dist-info/entry_points.txt
ctg_mcp_server-0.1.0.dist-info/RECORD
