Metadata-Version: 2.4
Name: ctg-mcp-server
Version: 0.1.0
Summary: Add your description here
Requires-Python: >=3.10
Requires-Dist: fastmcp>=2.5.1
Requires-Dist: pandas>=2.2.3
Requires-Dist: pytest>=8.3.5
Requires-Dist: pytrials>=1.0.0
